{
  "page-name": "reset-password",
  "page-type": "page",
  "class": "",
  "description": "La plataforma operativa del Grupo Hedgestone permite a sus clientes a establecer y editar sus cuentas. En esta página, los clientes también pueden depositar fondos y ver su historial de operaciones.",
  "array": [
    {
      "section": {
        "sectionName": "login-top-section",
        "sectionType": "reset-section",
        "class": "dark-background relative-position",
        "array": [
          {
            "block": {
              "class": "login-container",
              "array": [
                {
                  "headline": {
                    "title": "Restablezca su Contraseña",
                    "class": "hl1 text-center"
                  }
                },
                {
                  "headline": {
                    "class": "text-center form-headline",
                    "title": "Por favor, elija una contraseña segura para su cuenta."
                  }
                },
                {
                  "block": {
                    "class": "col-sm-8 col-md-6 col-xs-12 horizontal-center",
                    "array": [
                      {
                        "reset-form": {
                          "class": "",
                          "array": [
                            {
                              "new-form": {
                                "id": "reset-form",
                                "array": [
                                  {
                                    "form-group": {
                                      "class": "formGroup",
                                      "array": [
                                        {
                                          "block": {
                                            "array": [
                                              {
                                                "content-body": {
                                                  "text": "Nueva Contraseña",
                                                  "class": "formLabel"
                                                }
                                              },
                                              {
                                                "ng-field": {
                                                  "element": "input",
                                                  "dynamicAttrs": {
                                                    "ng-model": "",
                                                    "ng-class": "form-control",
                                                    "password": "",
                                                    "ng-maxlength": 25,
                                                    "ng-minlength": 6
                                                  },
                                                  "attrs": {
                                                    "placeholder": "",
                                                    "ng-pattern": "",
                                                    "name": "new_password",
                                                    "ng-required": true,
                                                    "type": "password",
                                                    "generic-validation": "ngField.ngFieldData"
                                                  },
                                                  "msgBox": {
                                                    "required": "Este campo es requerido",
                                                    "minlength": "La contraseña debe incluir por lo menos 6 letras.",
                                                    "maxlength": "La contraseña puede tener un máximo de 25 caracteres."
                                                  }
                                                }
                                              }
                                            ]
                                          }
                                        }
                                      ]
                                    }
                                  },
                                  {
                                    "form-group": {
                                      "class": "formGroup",
                                      "array": [
                                        {
                                          "block": {
                                            "array": [
                                              {
                                                "content-body": {
                                                  "text": "Confirme la Nueva Contraseña",
                                                  "class": "formLabel"
                                                }
                                              },
                                              {
                                                "ng-field": {
                                                  "element": "input",
                                                  "dynamicAttrs": {
                                                    "ng-model": "",
                                                    "ng-class": "form-control",
                                                    "confirm-password": ""
                                                  },
                                                  "attrs": {
                                                    "placeholder": "",
                                                    "ng-pattern": "",
                                                    "name": "Password",
                                                    "ng-required": true,
                                                    "type": "password"
                                                  },
                                                  "msgBox": {
                                                    "confirmPassword": "Las contraseñas no coinciden",
                                                    "required": "Este campo es requerido"
                                                  }
                                                }
                                              }
                                            ]
                                          }
                                        }
                                      ]
                                    }
                                  },
                                  {
                                    "ng-form-submit": {
                                      "class": "",
                                      "content": "iniciar sesión"
                                    }
                                  }
                                ]
                              }
                            }
                          ]
                        }
                      }
                    ]
                  }
                }
              ]
            }
          },
          {
            "block": {
              "class": "arrow",
              "background": "assets/images/sections/arrow.png"
            }
          }
        ]
      }
    },
    {
      "section": {
        "sectionName": "bottom-section",
        "sectionType": "open-account-section",
        "class": "bottom-section",
        "background": "",
        "containerClass": "",
        "array": [
          {
            "content": {
              "class": "",
              "array": [
                {
                  "ng-image": {
                    "image-name": "asset-test",
                    "src": "assets/icons/Logo.png",
                    "alt": "some asset",
                    "type": "img",
                    "class": "center-img",
                    "responsive": true
                  }
                },
                {
                  "block": {
                    "class": "text-center",
                    "array": [
                      {
                        "content-body": {
                          "class": "",
                          "text": "¿LISTO PARA COMENZAR?"
                        },
                        "precedence": 0
                      },
                      {
                        "headline": {
                          "title": "Poderoso. Dinámico. Sin límites.",
                          "class": "hl5"
                        },
                        "precedence": 1
                      },
                      {
                        "block": {
                          "class": "padded-block",
                          "array": [
                            {
                              "logged-in" : {
                                "array": [
                                  {
                                    "btn": {
                                      "class": "btn btn-transparent centered-btn",
                                      "title": "operación",
                                      "destination": "trade"
                                    },
                                    "precedence": 4
                                  },
                                  {
                                    "btn": {
                                      "class": "centered-btn",
                                      "title": "cómo funciona",
                                      "destination": "education"
                                    },
                                    "precedence": 5
                                  }
                                ]
                              }
                            },
                            {
                              "anonymous": {
                                "array": [
                                  {
                                    "btn": {
                                      "class": "btn btn-transparent centered-btn",
                                      "title": "abrir una cuenta",
                                      "destination": "create_account"
                                    },
                                    "precedence": 4
                                  },
                                  {
                                    "btn": {
                                      "class": "centered-btn",
                                      "title": "cómo funciona",
                                      "destination": "education"
                                    },
                                    "precedence": 5
                                  }
                                ]
                              }
                            }
                          ]
                        },
                        "precedence": 3
                      }
                    ]
                  }
                }
              ]
            }
          }
        ]
      }
    }
  ]
}